[{"type":"Entrées","items":[{"name":"Satay fait maison","info":"peanuts","options":[{"option":"boeuf","sizes":[{"size":"petit","price":"13.50"},{"size":"grand","price":"24"}]},{"option":"porc","sizes":[{"size":"petit","price":"12.50"},{"size":"grand","price":"23"}]},{"option":"poulet","sizes":[{"size":"petit","price":"12.50"},{"size":"grand","price":"23"}]},{"option":"crevettes","sizes":[{"size":"petit","price":"13.50"},{"size":"grand","price":"24"}]}]},{"name":"Rouleaux de printemps","options":[{"option":"poulet fait maison","price":"13"},{"option":"crevettes","price":"13"},{"option":"légumes","price":"12.50"}]},{"name":"Tofu au tamarin et aux arachides","info":"peanuts","sizes":[{"size":"petit","price":"10"},{"size":"grand","price":"15"}]},{"name":"Assortiment d'entrées","descr":"Rouleux de printemps crevettes et légumes et raviolis crevettes et légumes","sizes":[{"size":"petit","price":"14"},{"size":"grand","price":"26.50"}]}]},{"type":"Salades","items":[{"name":"Salade mixte","descr":"Sauce aux herbes thaïs et aux arachides","info":"peanuts","options":[{"option":"poulet - citronelle","sizes":[{"size":"petite","price":"12.50"},{"size":"grande","price":"22"}]},{"option":"boeuf - citronelle","sizes":[{"size":"petite","price":"14.50"},{"size":"grande","price":"25"}]},{"option":"crevettes - citronelle","sizes":[{"size":"petite","price":"13.50"},{"size":"grande","price":"24"}]},{"option":"calamars","sizes":[{"size":"petite","price":"13.50"},{"size":"grande","price":"24"}]}]},{"name":"Salade de vermicelles","info":"spicy","sizes":[{"size":"petite","price":"15"},{"size":"grande","price":"27"}]}]},{"type":"Nouilles en soupe","typeDescr":"(Nouilles de riz sans gluten)","items":[{"name":"Curry vert","options":[{"option":"poulet","price":"21.50"},{"option":"porc","price":"22"},{"option":"boeuf","price":"25"},{"option":"crevettes","price":"24"},{"option":"calamars","price":"22.50"},{"option":"tofu","price":"20.50"}]},{"name":"Curry rouge","options":[{"option":"poulet","price":"21.50"},{"option":"porc","price":"22"},{"option":"boeuf","price":"25"},{"option":"crevettes","price":"24"},{"option":"calamars","price":"22.50"},{"option":"tofu","price":"20.50"}]},{"name":"Curry jaune","info":"spicy","options":[{"option":"poulet","price":"21.50"},{"option":"boeuf","price":"25"},{"option":"tofu","price":"20.50"}]},{"name":"Chang Maï","descr":"spécialité du Nord de la Thaïlande","options":[{"option":"poulet","price":"21.50"},{"option":"boeuf","price":"25"},{"option":"tofu","price":"20.50"}]}]},{"type":"Nouilles en soupe","typeDescr":"(Nouilles de riz sans gluten)","items":[{"name":"Tom yum","info":"spicy","descr":"Au lait de coco et à la citronelle","options":[{"option":"poulet","price":"21.50"},{"option":"crevettes","price":"24"},{"option":"calamars","price":"22.50"},{"option":"tofu","price":"20.50"}]},{"name":"Tom kha","descr":"Au lait de coco et au galanga","options":[{"option":"poulet","price":"21.50"},{"option":"crevettes","price":"24"},{"option":"calamars","price":"22.50"},{"option":"tofu","price":"20.50"}]},{"name":"Sukhothai","descr":"Soupe claire aux herbes (idéale pour les régimes)","options":[{"option":"poulet","price":"21.50"},{"option":"porc","price":"22"},{"option":"boeuf","price":"25"},{"option":"crevettes","price":"24"},{"option":"calamars","price":"22.50"},{"option":"tofu","price":"20.50"}]}]},{"type":"Nouilles","typeDescr":"(Nouilles de riz sans gluten)","items":[{"name":"Pad thaï","descr":"Nouilles à la poële","info":"peanuts","options":[{"option":"poulet","price":"21.50"},{"option":"porc","price":"22"},{"option":"boeuf","price":"25"},{"option":"crevettes","price":"24"},{"option":"tofu","price":"20.50"}]},{"name":"Pattaya","descr":"Nouilles à la vapeur","info":"peanuts","options":[{"option":"poulet","price":"21.50"},{"option":"porc","price":"22"},{"option":"boeuf","price":"25"},{"option":"crevettes","price":"24"},{"option":"calamars","price":"22.50"},{"option":"tofu","price":"20.50"}]}]},{"type":"Plats avec du riz","items":[{"name":"Poulet croustillant","descr":"Sauce aux herbes","price":"23.50"},{"name":"Tom yum","info":"spicy","descr":"Au lait de coco et à la citronelle","options":[{"option":"poulet","price":"21.50"},{"option":"crevettes","price":"24"},{"option":"calamars","price":"22.50"},{"option":"tofu","price":"20.50"}]},{"name":"Tom kha","descr":"Au lait de coco et au galanga","options":[{"option":"poulet","price":"21.50"},{"option":"crevettes","price":"24"},{"option":"calamars","price":"22.50"},{"option":"tofu","price":"20.50"}]}]},{"type":"Plats avec du riz","items":[{"name":"Curry vert","options":[{"option":"poulet","price":"21.50"},{"option":"porc","price":"22"},{"option":"boeuf","price":"25"},{"option":"crevettes","price":"24"},{"option":"calamars","price":"22.50"},{"option":"tofu","price":"20.50"}]},{"name":"Curry rouge","options":[{"option":"poulet","price":"21.50"},{"option":"porc","price":"22"},{"option":"boeuf","price":"25"},{"option":"crevettes","price":"24"},{"option":"calamars","price":"22.50"},{"option":"tofu","price":"20.50"}]},{"name":"Portion de riz blanc","price":"4"}]},{"type":"Desserts","items":[{"name":"Mangue fraîche et riz gluant","price":"12"},{"name":"Raviolis à la banane et au miel","price":"12"},{"name":"Beignets de banane et lait condensé","price":"12"},{"name":"Beignet de glace à la noix de coco","price":"12"},{"name":"Crème glacée","descr":"Prix par boule","options":[{"option":"coco","price":"4"},{"option":"chocolat","price":"4"},{"option":"gingembre","price":"4"},{"option":"litchi","price":"4"}]}]},{"type":"Boissons","items":[{"name":"Eaux","options":[{"option":"Gazeuse","price":"?"},{"option":"Plate","price":"?"}]},{"name":"Sodas","options":[{"option":"Coca-cola","price":"?"},{"option":"Soda 2","price":"?"},{"option":"Soda 3","price":"?"}]},{"name":"Cafés","options":[{"option":"Expresso","price":"?"},{"option":"Normal","price":"?"}]},{"name":"Thés","options":[{"option":"Thé 1","price":"?"},{"option":"Thé 2","price":"?"}]}]},{"type":"Boissons","items":[{"name":"Vin blanc","options":[{"option":"Name of open wine (au verre)","price":"5"},{"option":"Name of bottle 1 (à la bouteille)","price":"?"},{"option":"Name of bottle 2 (à la bouteille)","price":"?"}]},{"name":"Vin rouge","options":[{"option":"Name of open wine (au verre)","price":"5"},{"option":"Name of bottle 1 (à la bouteille)","price":"?"},{"option":"Name of bottle 2 (à la bouteille)","price":"?"}]},{"name":"Vin rosé","options":[{"option":"Name of open wine (au verre)","price":"5"},{"option":"Name of bottle 1 (à la bouteille)","price":"?"},{"option":"Name of bottle 2 (à la bouteille)","price":"?"}]},{"name":"Bières","options":[{"option":"Singha","price":"5"},{"option":"Chang","price":"5"},{"option":"Other beer","price":"5"}]}]}]
